{
    "Ar36": {
        "error": 0.00027362650009771054,
        "error_type": "SEM",
        "filter_outliers_dict": {
            "filter_outliers": true,
            "iterations": 1,
            "std_devs": 2,
            "use_iqr_filtering": false,
            "use_standard_deviation_filtering": false
        },
        "fit": "linear",
        "fn": 201,
        "include_baseline_error": true,
        "n": 210,
        "outlier_excluded": [
            0,
            1,
            2,
            3,
            134,
            108,
            82,
            186,
            191
        ],
        "reviewed": true,
        "user_excluded": [],
        "value": 0.01910121796658154
    },
    "Ar37": {
        "error": 0.004455579040804458,
        "error_type": "SEM",
        "filter_outliers_dict": {
            "filter_outliers": true,
            "iterations": 1,
            "std_devs": 3,
            "use_iqr_filtering": false,
            "use_standard_deviation_filtering": false
        },
        "fit": "linear",
        "fn": 210,
        "include_baseline_error": true,
        "n": 210,
        "outlier_excluded": [],
        "reviewed": true,
        "user_excluded": [],
        "value": 0.06697514161700441
    },
    "Ar38": {
        "error": 0.003976605240797149,
        "error_type": "SEM",
        "filter_outliers_dict": {
            "filter_outliers": true,
            "iterations": 1,
            "std_devs": 3,
            "use_iqr_filtering": false,
            "use_standard_deviation_filtering": false
        },
        "fit": "linear",
        "fn": 208,
        "include_baseline_error": true,
        "n": 210,
        "outlier_excluded": [
            0,
            133
        ],
        "reviewed": true,
        "user_excluded": [],
        "value": 0.22022491589443577
    },
    "Ar39": {
        "error": 0.016484932181661333,
        "error_type": "SEM",
        "filter_outliers_dict": {
            "filter_outliers": true,
            "iterations": 1,
            "std_devs": 3,
            "use_iqr_filtering": false,
            "use_standard_deviation_filtering": false
        },
        "fit": "parabolic",
        "fn": 210,
        "include_baseline_error": true,
        "n": 210,
        "outlier_excluded": [],
        "reviewed": true,
        "user_excluded": [],
        "value": 11.22430070765843
    },
    "Ar40": {
        "error": 0.01960742007708296,
        "error_type": "SEM",
        "filter_outliers_dict": {
            "filter_outliers": true,
            "iterations": 1,
            "std_devs": 3,
            "use_iqr_filtering": false,
            "use_standard_deviation_filtering": false
        },
        "fit": "parabolic",
        "fn": 210,
        "include_baseline_error": true,
        "n": 210,
        "outlier_excluded": [],
        "reviewed": true,
        "user_excluded": [],
        "value": 56.78672794492479
    },
    "Ar41": {
        "error": 0.0032180290685826923,
        "error_type": "SEM",
        "filter_outliers_dict": {
            "filter_outliers": true,
            "iterations": 1,
            "std_devs": 2
        },
        "fit": "average",
        "value": 0.05444068282170125
    }
}