{
    "Ar36": {
        "error": 0.00024320969254609435,
        "error_type": "SEM",
        "filter_outliers_dict": {
            "filter_outliers": true,
            "iterations": 1,
            "std_devs": 2,
            "use_iqr_filtering": false,
            "use_standard_deviation_filtering": false
        },
        "fit": "linear",
        "fn": 205,
        "include_baseline_error": true,
        "n": 210,
        "outlier_excluded": [
            5,
            133,
            12,
            148,
            94
        ],
        "reviewed": true,
        "user_excluded": [],
        "value": 0.014741641447271612
    },
    "Ar37": {
        "error": 0.004395173815881183,
        "error_type": "SEM",
        "filter_outliers_dict": {
            "filter_outliers": true,
            "iterations": 1,
            "std_devs": 3,
            "use_iqr_filtering": false,
            "use_standard_deviation_filtering": false
        },
        "fit": "linear",
        "fn": 209,
        "include_baseline_error": true,
        "n": 210,
        "outlier_excluded": [
            155
        ],
        "reviewed": true,
        "user_excluded": [],
        "value": 0.03824101812573498
    },
    "Ar38": {
        "error": 0.003960671033434618,
        "error_type": "SEM",
        "filter_outliers_dict": {
            "filter_outliers": true,
            "iterations": 1,
            "std_devs": 3,
            "use_iqr_filtering": false,
            "use_standard_deviation_filtering": false
        },
        "fit": "linear",
        "fn": 209,
        "include_baseline_error": true,
        "n": 210,
        "outlier_excluded": [
            29
        ],
        "reviewed": true,
        "user_excluded": [],
        "value": 0.13959943062546076
    },
    "Ar39": {
        "error": 0.015141302295522692,
        "error_type": "SEM",
        "filter_outliers_dict": {
            "filter_outliers": true,
            "iterations": 1,
            "std_devs": 3,
            "use_iqr_filtering": false,
            "use_standard_deviation_filtering": false
        },
        "fit": "parabolic",
        "fn": 208,
        "include_baseline_error": true,
        "n": 210,
        "outlier_excluded": [
            170,
            143
        ],
        "reviewed": true,
        "user_excluded": [],
        "value": 4.697022677896275
    },
    "Ar40": {
        "error": 0.014189036553445371,
        "error_type": "SEM",
        "filter_outliers_dict": {
            "filter_outliers": true,
            "iterations": 1,
            "std_devs": 3,
            "use_iqr_filtering": false,
            "use_standard_deviation_filtering": false
        },
        "fit": "parabolic",
        "fn": 209,
        "include_baseline_error": true,
        "n": 210,
        "outlier_excluded": [
            199
        ],
        "reviewed": true,
        "user_excluded": [],
        "value": 22.556782821772053
    },
    "Ar41": {
        "error": 0.0032757289035291477,
        "error_type": "SEM",
        "filter_outliers_dict": {
            "filter_outliers": true,
            "iterations": 1,
            "std_devs": 2
        },
        "fit": "average",
        "value": 0.05000219570033703
    }
}