{
    "Ar36": {
        "error": 0.0003201587708996973,
        "error_type": "",
        "fit": "previous",
        "references": [
            {
                "exclude": false,
                "record_id": "bu-FC-J-21179"
            }
        ],
        "value": 0.0227061864624054
    },
    "Ar37": {
        "error": 0.005024257847217755,
        "error_type": "",
        "fit": "previous",
        "references": [
            {
                "exclude": false,
                "record_id": "bu-FC-J-21179"
            }
        ],
        "value": 0.06379495786402722
    },
    "Ar38": {
        "error": 0.004133235049412346,
        "error_type": "",
        "fit": "previous",
        "references": [
            {
                "exclude": false,
                "record_id": "bu-FC-J-21179"
            }
        ],
        "value": 0.0338419288694593
    },
    "Ar39": {
        "error": 0.009858440573555899,
        "error_type": "",
        "fit": "previous",
        "references": [
            {
                "exclude": false,
                "record_id": "bu-FC-J-21179"
            }
        ],
        "value": 0.10267773296531005
    },
    "Ar40": {
        "error": 0.009319721075970552,
        "error_type": "",
        "fit": "previous",
        "references": [
            {
                "exclude": false,
                "record_id": "bu-FC-J-21179"
            }
        ],
        "value": 2.598779286937407
    },
    "Ar41": {
        "error": 0.0038381381401128662,
        "error_type": "",
        "fit": "previous",
        "references": [
            {
                "exclude": false,
                "record_id": "bu-FC-J-21179"
            }
        ],
        "value": 0.0635470499192659
    }
}