{
    "Ar36": {
        "error": 0.00027594009630092293,
        "error_type": "SEM",
        "filter_outliers_dict": {
            "filter_outliers": true,
            "iterations": 1,
            "std_devs": 2,
            "use_iqr_filtering": false,
            "use_standard_deviation_filtering": false
        },
        "fit": "linear",
        "fn": 202,
        "include_baseline_error": true,
        "n": 210,
        "outlier_excluded": [
            0,
            1,
            2,
            162,
            4,
            164,
            112,
            113
        ],
        "reviewed": true,
        "user_excluded": [],
        "value": 0.02556634937608247
    },
    "Ar37": {
        "error": 0.004280201447947384,
        "error_type": "SEM",
        "filter_outliers_dict": {
            "filter_outliers": true,
            "iterations": 1,
            "std_devs": 3,
            "use_iqr_filtering": false,
            "use_standard_deviation_filtering": false
        },
        "fit": "linear",
        "fn": 209,
        "include_baseline_error": true,
        "n": 210,
        "outlier_excluded": [
            49
        ],
        "reviewed": true,
        "user_excluded": [],
        "value": 0.14457413642577127
    },
    "Ar38": {
        "error": 0.003772685793668357,
        "error_type": "SEM",
        "filter_outliers_dict": {
            "filter_outliers": true,
            "iterations": 1,
            "std_devs": 3,
            "use_iqr_filtering": false,
            "use_standard_deviation_filtering": false
        },
        "fit": "linear",
        "fn": 209,
        "include_baseline_error": true,
        "n": 210,
        "outlier_excluded": [
            2
        ],
        "reviewed": true,
        "user_excluded": [],
        "value": 0.5365388037991914
    },
    "Ar39": {
        "error": 0.020275938132959206,
        "error_type": "SEM",
        "filter_outliers_dict": {
            "filter_outliers": true,
            "iterations": 1,
            "std_devs": 3,
            "use_iqr_filtering": false,
            "use_standard_deviation_filtering": false
        },
        "fit": "parabolic",
        "fn": 210,
        "include_baseline_error": true,
        "n": 210,
        "outlier_excluded": [],
        "reviewed": true,
        "user_excluded": [],
        "value": 37.5203764599104
    },
    "Ar40": {
        "error": 0.025500665581654237,
        "error_type": "SEM",
        "filter_outliers_dict": {
            "filter_outliers": true,
            "iterations": 1,
            "std_devs": 3,
            "use_iqr_filtering": false,
            "use_standard_deviation_filtering": false
        },
        "fit": "parabolic",
        "fn": 210,
        "include_baseline_error": true,
        "n": 210,
        "outlier_excluded": [],
        "reviewed": true,
        "user_excluded": [],
        "value": 123.29395181733773
    },
    "Ar41": {
        "error": 0.00366796052640296,
        "error_type": "SEM",
        "filter_outliers_dict": {
            "filter_outliers": true,
            "iterations": 1,
            "std_devs": 2
        },
        "fit": "average",
        "value": 0.06719156956051935
    }
}