{
    "Ar36": {
        "error": 0.00016676969204334856, 
        "fit": "previous", 
        "references": [
            {
                "exclude": false, 
                "record_id": "bc-02-J-226"
            }
        ], 
        "value": 0.004451764885939799
    }, 
    "Ar37": {
        "error": 0.005545517599638265, 
        "fit": "previous", 
        "references": [
            {
                "exclude": false, 
                "record_id": "bc-02-J-226"
            }
        ], 
        "value": 0.04577989802407856
    }, 
    "Ar38": {
        "error": 0.0021428114685929827, 
        "fit": "previous", 
        "references": [
            {
                "exclude": false, 
                "record_id": "bc-02-J-226"
            }
        ], 
        "value": 0.007185428460273362
    }, 
    "Ar39": {
        "error": 0.009433146535288716, 
        "fit": "previous", 
        "references": [
            {
                "exclude": false, 
                "record_id": "bc-02-J-226"
            }
        ], 
        "value": 0.024146353236362918
    }, 
    "Ar40": {
        "error": 0.006933247918599147, 
        "fit": "previous", 
        "references": [
            {
                "exclude": false, 
                "record_id": "bc-02-J-226"
            }
        ], 
        "value": 0.19224058431961477
    }, 
    "PM41": {
        "error": 0.06685945741751526, 
        "fit": "previous", 
        "references": [
            {
                "exclude": false, 
                "record_id": "bc-02-J-226"
            }
        ], 
        "value": 0.01751391633375088
    }
}