{
    "Ar36": {
        "error": 0.0002788684948677565,
        "error_type": "SEM",
        "filter_outliers_dict": {
            "filter_outliers": true,
            "iterations": 1,
            "std_devs": 2,
            "use_iqr_filtering": false,
            "use_standard_deviation_filtering": false
        },
        "fit": "linear",
        "fn": 203,
        "include_baseline_error": true,
        "n": 210,
        "outlier_excluded": [
            0,
            2,
            3,
            35,
            11,
            78,
            189
        ],
        "reviewed": true,
        "user_excluded": [],
        "value": 0.019551050404263595
    },
    "Ar37": {
        "error": 0.005086227718682332,
        "error_type": "SEM",
        "filter_outliers_dict": {
            "filter_outliers": true,
            "iterations": 1,
            "std_devs": 3,
            "use_iqr_filtering": false,
            "use_standard_deviation_filtering": false
        },
        "fit": "linear",
        "fn": 207,
        "include_baseline_error": true,
        "n": 210,
        "outlier_excluded": [
            45,
            46,
            47
        ],
        "reviewed": true,
        "user_excluded": [],
        "value": 0.12908015671521333
    },
    "Ar38": {
        "error": 0.004017694810070997,
        "error_type": "SEM",
        "filter_outliers_dict": {
            "filter_outliers": true,
            "iterations": 1,
            "std_devs": 3,
            "use_iqr_filtering": false,
            "use_standard_deviation_filtering": false
        },
        "fit": "linear",
        "fn": 210,
        "include_baseline_error": true,
        "n": 210,
        "outlier_excluded": [],
        "reviewed": true,
        "user_excluded": [],
        "value": 0.24844117736881596
    },
    "Ar39": {
        "error": 0.017045648944753338,
        "error_type": "SEM",
        "filter_outliers_dict": {
            "filter_outliers": true,
            "iterations": 1,
            "std_devs": 3,
            "use_iqr_filtering": false,
            "use_standard_deviation_filtering": false
        },
        "fit": "parabolic",
        "fn": 210,
        "include_baseline_error": true,
        "n": 210,
        "outlier_excluded": [],
        "reviewed": true,
        "user_excluded": [],
        "value": 13.244380540849155
    },
    "Ar40": {
        "error": 0.027038261675842293,
        "error_type": "SEM",
        "filter_outliers_dict": {
            "filter_outliers": true,
            "iterations": 1,
            "std_devs": 3,
            "use_iqr_filtering": false,
            "use_standard_deviation_filtering": false
        },
        "fit": "parabolic",
        "fn": 210,
        "include_baseline_error": true,
        "n": 210,
        "outlier_excluded": [],
        "reviewed": true,
        "user_excluded": [],
        "value": 112.34818515351074
    },
    "Ar41": {
        "error": 0.0031914475500598857,
        "error_type": "SEM",
        "filter_outliers_dict": {
            "filter_outliers": true,
            "iterations": 1,
            "std_devs": 2
        },
        "fit": "average",
        "value": 0.06707668386379384
    }
}