{
    "AX": {
        "error": 0.007364771262082209,
        "error_type": "SEM",
        "filter_outliers_dict": {
            "filter_outliers": true,
            "iterations": 1,
            "std_devs": 2
        },
        "fit": "average",
        "modifier_error": 0.0,
        "modifier_value": 0.0,
        "value": -0.23752360875066275
    },
    "CDD": {
        "error": 1.2879710719075561e-05,
        "error_type": "SEM",
        "filter_outliers_dict": {
            "filter_outliers": true,
            "iterations": 1,
            "std_devs": 10
        },
        "fit": "average",
        "modifier_error": 3.182413309197805e-05,
        "modifier_value": 0.00022878689742963302,
        "value": 0.0002610200503018225
    },
    "H1": {
        "error": 0.00845555824525024,
        "error_type": "SEM",
        "filter_outliers_dict": {
            "filter_outliers": true,
            "iterations": 1,
            "std_devs": 2
        },
        "fit": "average",
        "modifier_error": 0.0,
        "modifier_value": 0.0,
        "value": 0.09587973863944801
    },
    "H2": {
        "error": 0.008177382466382688,
        "error_type": "SEM",
        "filter_outliers_dict": {
            "filter_outliers": true,
            "iterations": 1,
            "std_devs": 2
        },
        "fit": "average",
        "modifier_error": 0.0,
        "modifier_value": 0.0,
        "value": 0.007816357977795016
    },
    "L1": {
        "error": 0.0035469221425449685,
        "error_type": "SEM",
        "filter_outliers_dict": {
            "filter_outliers": true,
            "iterations": 1,
            "std_devs": 2
        },
        "fit": "average",
        "modifier_error": 0.0,
        "modifier_value": 0.0,
        "value": 0.06725311008924993
    },
    "L2": {
        "error": 0.004842530236883838,
        "error_type": "SEM",
        "filter_outliers_dict": {
            "filter_outliers": true,
            "iterations": 1,
            "std_devs": 2
        },
        "fit": "average",
        "modifier_error": 0.0,
        "modifier_value": 0.0,
        "value": -0.034500006246163534
    }
}