{
    "Ar36": {
        "error": 0.0002864888238516936,
        "error_type": "SEM",
        "filter_outliers_dict": {
            "filter_outliers": true,
            "iterations": 1,
            "std_devs": 2,
            "use_iqr_filtering": false,
            "use_standard_deviation_filtering": false
        },
        "fit": "linear",
        "fn": 200,
        "include_baseline_error": true,
        "n": 210,
        "outlier_excluded": [
            0,
            1,
            2,
            3,
            138,
            207,
            21,
            56,
            184,
            95
        ],
        "reviewed": true,
        "user_excluded": [],
        "value": 0.01942538579286554
    },
    "Ar37": {
        "error": 0.004686479183756372,
        "error_type": "SEM",
        "filter_outliers_dict": {
            "filter_outliers": true,
            "iterations": 1,
            "std_devs": 3,
            "use_iqr_filtering": false,
            "use_standard_deviation_filtering": false
        },
        "fit": "linear",
        "fn": 210,
        "include_baseline_error": true,
        "n": 210,
        "outlier_excluded": [],
        "reviewed": true,
        "user_excluded": [],
        "value": 0.06596157553014975
    },
    "Ar38": {
        "error": 0.003757845189615733,
        "error_type": "SEM",
        "filter_outliers_dict": {
            "filter_outliers": true,
            "iterations": 1,
            "std_devs": 3,
            "use_iqr_filtering": false,
            "use_standard_deviation_filtering": false
        },
        "fit": "linear",
        "fn": 208,
        "include_baseline_error": true,
        "n": 210,
        "outlier_excluded": [
            106,
            127
        ],
        "reviewed": true,
        "user_excluded": [],
        "value": 0.18935291366306578
    },
    "Ar39": {
        "error": 0.017002159624814585,
        "error_type": "SEM",
        "filter_outliers_dict": {
            "filter_outliers": true,
            "iterations": 1,
            "std_devs": 3,
            "use_iqr_filtering": false,
            "use_standard_deviation_filtering": false
        },
        "fit": "parabolic",
        "fn": 210,
        "include_baseline_error": true,
        "n": 210,
        "outlier_excluded": [],
        "reviewed": true,
        "user_excluded": [],
        "value": 8.510386777550387
    },
    "Ar40": {
        "error": 0.021752957593647947,
        "error_type": "SEM",
        "filter_outliers_dict": {
            "filter_outliers": true,
            "iterations": 1,
            "std_devs": 3,
            "use_iqr_filtering": false,
            "use_standard_deviation_filtering": false
        },
        "fit": "parabolic",
        "fn": 210,
        "include_baseline_error": true,
        "n": 210,
        "outlier_excluded": [],
        "reviewed": true,
        "user_excluded": [],
        "value": 56.79887007309026
    },
    "Ar41": {
        "error": 0.0034854804670499608,
        "error_type": "SEM",
        "filter_outliers_dict": {
            "filter_outliers": true,
            "iterations": 1,
            "std_devs": 2
        },
        "fit": "average",
        "value": 0.06557539585351263
    }
}