{
    "AX": {
        "error": 0.005141274801298213, 
        "filter_outliers_dict": {
            "filter_outliers": true, 
            "iterations": 1, 
            "std_devs": 2
        }, 
        "fit": "average", 
        "value": -0.05917005739319062
    }, 
    "CDD": {
        "error": 3.7716850228618652e-06, 
        "filter_outliers_dict": {
            "filter_outliers": true, 
            "iterations": 1, 
            "std_devs": 10
        }, 
        "fit": "average", 
        "value": 1.2405450933469749e-05
    }, 
    "H1": {
        "error": 0.0038688666295468295, 
        "filter_outliers_dict": {
            "filter_outliers": true, 
            "iterations": 1, 
            "std_devs": 2
        }, 
        "fit": "average", 
        "value": -0.03627511373599623
    }, 
    "H2": {
        "error": 0.004630564432770583, 
        "filter_outliers_dict": {
            "filter_outliers": true, 
            "iterations": 1, 
            "std_devs": 2
        }, 
        "fit": "average", 
        "value": -0.19885280224972493
    }, 
    "L1": {
        "error": 0.0017660863485229618, 
        "filter_outliers_dict": {
            "filter_outliers": true, 
            "iterations": 1, 
            "std_devs": 2
        }, 
        "fit": "average", 
        "value": -0.026617653914896382
    }, 
    "L2": {
        "error": 0.0044525249557477355, 
        "filter_outliers_dict": {
            "filter_outliers": true, 
            "iterations": 1, 
            "std_devs": 2
        }, 
        "fit": "average", 
        "value": -0.02056072476221364
    }
}