{
    "Ar36": {
        "error": 0.0002737700840717956,
        "error_type": "SEM",
        "filter_outliers_dict": {
            "filter_outliers": true,
            "iterations": 1,
            "std_devs": 2,
            "use_iqr_filtering": false,
            "use_standard_deviation_filtering": false
        },
        "fit": "linear",
        "fn": 200,
        "include_baseline_error": true,
        "n": 210,
        "outlier_excluded": [
            0,
            2,
            3,
            4,
            99,
            6,
            164,
            9,
            50,
            189
        ],
        "reviewed": true,
        "user_excluded": [],
        "value": 0.020941374253831493
    },
    "Ar37": {
        "error": 0.0051744293301913356,
        "error_type": "SEM",
        "filter_outliers_dict": {
            "filter_outliers": true,
            "iterations": 1,
            "std_devs": 3,
            "use_iqr_filtering": false,
            "use_standard_deviation_filtering": false
        },
        "fit": "linear",
        "fn": 209,
        "include_baseline_error": true,
        "n": 210,
        "outlier_excluded": [
            145
        ],
        "reviewed": true,
        "user_excluded": [],
        "value": 0.09778485377287673
    },
    "Ar38": {
        "error": 0.003982719668819073,
        "error_type": "SEM",
        "filter_outliers_dict": {
            "filter_outliers": true,
            "iterations": 1,
            "std_devs": 3,
            "use_iqr_filtering": false,
            "use_standard_deviation_filtering": false
        },
        "fit": "linear",
        "fn": 210,
        "include_baseline_error": true,
        "n": 210,
        "outlier_excluded": [],
        "reviewed": true,
        "user_excluded": [],
        "value": 0.18692080566007502
    },
    "Ar39": {
        "error": 0.017428881147567438,
        "error_type": "SEM",
        "filter_outliers_dict": {
            "filter_outliers": true,
            "iterations": 1,
            "std_devs": 3,
            "use_iqr_filtering": false,
            "use_standard_deviation_filtering": false
        },
        "fit": "parabolic",
        "fn": 209,
        "include_baseline_error": true,
        "n": 210,
        "outlier_excluded": [
            36
        ],
        "reviewed": true,
        "user_excluded": [],
        "value": 7.912493349335046
    },
    "Ar40": {
        "error": 0.02244924256743959,
        "error_type": "SEM",
        "filter_outliers_dict": {
            "filter_outliers": true,
            "iterations": 1,
            "std_devs": 3,
            "use_iqr_filtering": false,
            "use_standard_deviation_filtering": false
        },
        "fit": "parabolic",
        "fn": 210,
        "include_baseline_error": true,
        "n": 210,
        "outlier_excluded": [],
        "reviewed": true,
        "user_excluded": [],
        "value": 70.25302091113946
    },
    "Ar41": {
        "error": 0.00349365507357629,
        "error_type": "SEM",
        "filter_outliers_dict": {
            "filter_outliers": true,
            "iterations": 1,
            "std_devs": 2
        },
        "fit": "average",
        "value": 0.05665823744330501
    }
}